pyassignmentgrader/__init__.py
pyassignmentgrader/cli.py
pyassignmentgrader/handlers/python_function.py
pyassignmentgrader/results.py
pyassignmentgrader/rubric.py
pyassignmentgrader/ui/console.py
pyassignmentgrader/utils.py
pyassignmentgrader-0.3.dist-info/METADATA
pyassignmentgrader-0.3.dist-info/WHEEL
pyassignmentgrader-0.3.dist-info/entry_points.txt
pyassignmentgrader-0.3.dist-info/RECORD
